minigrad/__init__.py
minigrad/loss.py
minigrad/nn.py
minigrad/optim.py
minigrad/tensor.py
minigrad_python-0.1.1.dist-info/METADATA
minigrad_python-0.1.1.dist-info/WHEEL
minigrad_python-0.1.1.dist-info/top_level.txt
minigrad_python-0.1.1.dist-info/RECORD
