Metadata-Version: 2.1
Name: minigrad-python
Version: 0.1.1
Summary: A minimal deep learning framework with automatic differentiation
Home-page: https://github.com/udaysankar01/minigrad
Author: Uday Sankar
License: MIT
Classifier: Programming Language :: Python :: 3
Classifier: License :: OSI Approved :: MIT License
Classifier: Operating System :: OS Independent
Requires-Python: >=3.6
Requires-Dist: numpy>=1.21.0
Requires-Dist: graphviz>=0.20.0
Requires-Dist: cupy-cuda12x
